{"components_alert.md":"4854c401","components_avatar.md":"f10a5af0","components_back-top.md":"0f9db717","components_badge.md":"e01edc0b","components_breadcrumb.md":"1144fbcb","components_button.md":"824ccb49","components_calendar.md":"3e3ed15c","components_card.md":"b780ab57","components_checkbox.md":"545c5d50","components_close-btn.md":"ad0045ad","components_color.md":"a078d6fb","components_dialog.md":"7b599d30","components_divider.md":"4ff0d4cd","components_drawer.md":"5c294b97","components_empty.md":"2556be5d","components_expand-card.md":"1922e3ba","components_image-preview.md":"3af4430a","components_image.md":"8610c6c9","components_input.md":"c9808335","components_layout.md":"32de667e","components_link.md":"075916d2","components_list.md":"dba558ba","components_loading-bar.md":"d25c2a24","components_loading.md":"b558d809","components_message.md":"e81957b6","components_notification.md":"3ba08e05","components_page-header.md":"41a3c0de","components_popup.md":"1b95ad7a","components_progress.md":"9732c1da","components_radio.md":"c6eec16a","components_rate.md":"d825e461","components_ripple.md":"87c3b3c8","components_skeleton.md":"ade71fb6","components_space.md":"00ba69bc","components_sticky-card.md":"717750b9","components_svg-icon.md":"d4533771","components_swap.md":"887b9ac3","components_switch.md":"fbb116f2","components_tag.md":"3aff2077","components_text.md":"85a89e3b","components_toolbar.md":"2bcde29e","components_tooltip.md":"cc3a1d8c","components_tree.md":"8f634a86","components_watermark.md":"199b73c3","docs_changelog.md":"022d7630","docs_contributing.md":"26ad4f70","docs_import.md":"da0ad527","docs_install.md":"e3b74358","docs_introduce.md":"9df5d2cf","docs_join.md":"e80c33bd","docs_milepost.md":"a8c766ae","index.md":"90bdb320"}
